qbquantum/__init__.py
qbquantum/__main__.py
qbquantum/building/__init__.py
qbquantum/building/build_tools.py
qbquantum/building/compiling.py
qbquantum/building/runner.py
qbquantum/helpers.py
qbquantum/initializing.py
qbquantum/managing/__init__.py
qbquantum/managing/filegenerator.py
qbquantum/managing/installing.py
qbquantum/packaging/__init__.py
qbquantum/packaging/packager.py
qbquantum/packaging/publisher.py
qbquantum-0.1.3.dist-info/entry_points.txt
qbquantum-0.1.3.dist-info/METADATA
qbquantum-0.1.3.dist-info/WHEEL
qbquantum-0.1.3.dist-info/RECORD
